korlibrarycheater/KorLibraryCheater.py
korlibrarycheater/__init__.py
korlibrarycheater-0.1.2.dist-info/METADATA
korlibrarycheater-0.1.2.dist-info/WHEEL
korlibrarycheater-0.1.2.dist-info/entry_points.txt
korlibrarycheater-0.1.2.dist-info/top_level.txt
korlibrarycheater-0.1.2.dist-info/RECORD
