Metadata-Version: 2.4
Name: korlibrarycheater
Version: 0.1.2
Summary: 파이썬 라이브러리 탐색 도구
Home-page: https://github.com/ppenn0411/KorLibraryCheater
Author: ppenn0411
Classifier: Programming Language :: Python :: 3
Classifier: Operating System :: OS Independent
Requires-Python: >=3.6
Dynamic: author
Dynamic: classifier
Dynamic: home-page
Dynamic: requires-python
Dynamic: summary
